{"apiVersion":"apps/v1","kind":"Deployment","metadata":{"annotations":{"deployment.kubernetes.io/revision":"5","kubectl.kubernetes.io/last-applied-configuration":"{\"apiVersion\":\"apps/v1\",\"kind\":\"Deployment\",\"metadata\":{\"annotations\":{\"deployment.kubernetes.io/revision\":\"4\",\"kubesphere.io/creator\":\"zhu\"},\"creationTimestamp\":\"2022-06-02T07:05:27Z\",\"generation\":5,\"labels\":{\"app\":\"admin-agent-ui\",\"version\":\"v1\"},\"name\":\"admin-agent-ui-v1\",\"namespace\":\"srqz-bl003-admin\",\"resourceVersion\":\"141293121\",\"uid\":\"3c290fb5-c815-4e68-9f6b-4fe4ce3c0a04\"},\"spec\":{\"progressDeadlineSeconds\":600,\"replicas\":1,\"revisionHistoryLimit\":10,\"selector\":{\"matchLabels\":{\"app\":\"admin-agent-ui\",\"version\":\"v1\"}},\"strategy\":{\"rollingUpdate\":{\"maxSurge\":\"25%\",\"maxUnavailable\":\"25%\"},\"type\":\"RollingUpdate\"},\"template\":{\"metadata\":{\"creationTimestamp\":null,\"labels\":{\"app\":\"admin-agent-ui\",\"version\":\"v1\"}},\"spec\":{\"containers\":[{\"image\":\"harbor6.wns8.io/srqz/agent-web-ui/admin_agent_web_ui:1.0.9\",\"imagePullPolicy\":\"IfNotPresent\",\"name\":\"container-ef2ib6\",\"ports\":[{\"containerPort\":8080,\"name\":\"tcp-8080\",\"protocol\":\"TCP\"}],\"resources\":{},\"terminationMessagePath\":\"/dev/termination-log\",\"terminationMessagePolicy\":\"File\"}],\"dnsPolicy\":\"ClusterFirst\",\"restartPolicy\":\"Always\",\"schedulerName\":\"default-scheduler\",\"securityContext\":{},\"serviceAccount\":\"default\",\"serviceAccountName\":\"default\",\"terminationGracePeriodSeconds\":30}}},\"status\":{\"availableReplicas\":1,\"conditions\":[{\"lastTransitionTime\":\"2022-06-02T07:05:29Z\",\"lastUpdateTime\":\"2022-06-02T07:05:29Z\",\"message\":\"Deployment has minimum availability.\",\"reason\":\"MinimumReplicasAvailable\",\"status\":\"True\",\"type\":\"Available\"},{\"lastTransitionTime\":\"2022-06-02T07:05:27Z\",\"lastUpdateTime\":\"2022-06-15T05:58:34Z\",\"message\":\"ReplicaSet \\\"admin-agent-ui-v1-57bb69cbb7\\\" has successfully progressed.\",\"reason\":\"NewReplicaSetAvailable\",\"status\":\"True\",\"type\":\"Progressing\"}],\"observedGeneration\":5,\"readyReplicas\":1,\"replicas\":1,\"updatedReplicas\":1}}\n"},"generation":8,"labels":{"app":"admin-agent-ui","version":"v1"},"name":"admin-agent-ui-v1","namespace":"srqz-bl003-admin"},"spec":{"progressDeadlineSeconds":600,"replicas":0,"revisionHistoryLimit":10,"selector":{"matchLabels":{"app":"admin-agent-ui","version":"v1"}},"strategy":{"rollingUpdate":{"maxSurge":"25%","maxUnavailable":"25%"},"type":"RollingUpdate"},"template":{"metadata":{"creationTimestamp":null,"labels":{"app":"admin-agent-ui","version":"v1"}},"spec":{"containers":[{"image":"harbor62.wns8.io/srqz/agent-web-ui/admin_agent_web_ui:1.0.9","imagePullPolicy":"IfNotPresent","name":"container-ef2ib6","ports":[{"containerPort":8080,"name":"tcp-8080","protocol":"TCP"}],"resources":{},"terminationMessagePath":"/dev/termination-log","terminationMessagePolicy":"File"}],"dnsPolicy":"ClusterFirst","restartPolicy":"Always","schedulerName":"default-scheduler","securityContext":{},"serviceAccount":"default","serviceAccountName":"default","terminationGracePeriodSeconds":30}}}}
{"apiVersion":"apps/v1","kind":"Deployment","metadata":{"annotations":{"deployment.kubernetes.io/revision":"7","kubectl.kubernetes.io/last-applied-configuration":"{\"apiVersion\":\"apps/v1\",\"kind\":\"Deployment\",\"metadata\":{\"annotations\":{\"deployment.kubernetes.io/revision\":\"5\",\"kubesphere.io/creator\":\"zhu\"},\"creationTimestamp\":\"2022-06-02T07:06:26Z\",\"generation\":6,\"labels\":{\"app\":\"admin-agent\",\"version\":\"v1\"},\"name\":\"admin-agent-v1\",\"namespace\":\"srqz-bl003-admin\",\"resourceVersion\":\"141293122\",\"uid\":\"20f24494-6380-4872-9f48-183d98550da7\"},\"spec\":{\"progressDeadlineSeconds\":600,\"replicas\":1,\"revisionHistoryLimit\":10,\"selector\":{\"matchLabels\":{\"app\":\"admin-agent\",\"version\":\"v1\"}},\"strategy\":{\"rollingUpdate\":{\"maxSurge\":\"25%\",\"maxUnavailable\":\"25%\"},\"type\":\"RollingUpdate\"},\"template\":{\"metadata\":{\"creationTimestamp\":null,\"labels\":{\"app\":\"admin-agent\",\"version\":\"v1\"}},\"spec\":{\"containers\":[{\"env\":[{\"name\":\"APPHOST\",\"valueFrom\":{\"configMapKeyRef\":{\"key\":\"APPHOST\",\"name\":\"admin-http-config\"}}},{\"name\":\"SRQZDEBUG\",\"valueFrom\":{\"configMapKeyRef\":{\"key\":\"SRQZDEBUG\",\"name\":\"admin-http-config\"}}}],\"envFrom\":[{\"configMapRef\":{\"name\":\"app-server-config\"}},{\"configMapRef\":{\"name\":\"admin-http-config\"}}],\"image\":\"harbor6.wns8.io/srqz/admin-agent:1.0.5\",\"imagePullPolicy\":\"IfNotPresent\",\"name\":\"container-kt78kl\",\"ports\":[{\"containerPort\":81,\"name\":\"http-8082\",\"protocol\":\"TCP\"}],\"resources\":{},\"terminationMessagePath\":\"/dev/termination-log\",\"terminationMessagePolicy\":\"File\"}],\"dnsPolicy\":\"ClusterFirst\",\"restartPolicy\":\"Always\",\"schedulerName\":\"default-scheduler\",\"securityContext\":{},\"serviceAccount\":\"default\",\"serviceAccountName\":\"default\",\"terminationGracePeriodSeconds\":30}}},\"status\":{\"availableReplicas\":1,\"conditions\":[{\"lastTransitionTime\":\"2022-06-02T07:07:11Z\",\"lastUpdateTime\":\"2022-06-02T07:07:11Z\",\"message\":\"Deployment has minimum availability.\",\"reason\":\"MinimumReplicasAvailable\",\"status\":\"True\",\"type\":\"Available\"},{\"lastTransitionTime\":\"2022-06-02T07:06:26Z\",\"lastUpdateTime\":\"2022-06-13T04:13:53Z\",\"message\":\"ReplicaSet \\\"admin-agent-v1-6c9cbc9d74\\\" has successfully progressed.\",\"reason\":\"NewReplicaSetAvailable\",\"status\":\"True\",\"type\":\"Progressing\"}],\"observedGeneration\":6,\"readyReplicas\":1,\"replicas\":1,\"updatedReplicas\":1}}\n"},"generation":10,"labels":{"app":"admin-agent","version":"v1"},"name":"admin-agent-v1","namespace":"srqz-bl003-admin"},"spec":{"progressDeadlineSeconds":600,"replicas":0,"revisionHistoryLimit":10,"selector":{"matchLabels":{"app":"admin-agent","version":"v1"}},"strategy":{"rollingUpdate":{"maxSurge":"25%","maxUnavailable":"25%"},"type":"RollingUpdate"},"template":{"metadata":{"creationTimestamp":null,"labels":{"app":"admin-agent","version":"v1"}},"spec":{"containers":[{"env":[{"name":"APPHOST","valueFrom":{"configMapKeyRef":{"key":"APPHOST","name":"admin-http-config"}}},{"name":"SRQZDEBUG","valueFrom":{"configMapKeyRef":{"key":"SRQZDEBUG","name":"admin-http-config"}}}],"envFrom":[{"configMapRef":{"name":"app-server-config"}},{"configMapRef":{"name":"admin-http-config"}}],"image":"harbor6.wns8.io/srqz/admin-agent:1.0.5","imagePullPolicy":"IfNotPresent","name":"container-kt78kl","ports":[{"containerPort":81,"name":"http-8082","protocol":"TCP"}],"resources":{},"terminationMessagePath":"/dev/termination-log","terminationMessagePolicy":"File"}],"dnsPolicy":"ClusterFirst","restartPolicy":"Always","schedulerName":"default-scheduler","securityContext":{},"serviceAccount":"default","serviceAccountName":"default","terminationGracePeriodSeconds":30}}}}
{"apiVersion":"apps/v1","kind":"Deployment","metadata":{"annotations":{"deployment.kubernetes.io/revision":"45","kubectl.kubernetes.io/last-applied-configuration":"{\"apiVersion\":\"apps/v1\",\"kind\":\"Deployment\",\"metadata\":{\"annotations\":{\"deployment.kubernetes.io/revision\":\"41\",\"kubesphere.io/creator\":\"zhu\"},\"creationTimestamp\":\"2022-04-15T22:40:32Z\",\"generation\":42,\"labels\":{\"app\":\"admin-http2\",\"version\":\"v1\"},\"name\":\"admin-http2-v1\",\"namespace\":\"srqz-bl003-admin\",\"resourceVersion\":\"141293126\",\"uid\":\"b34ec441-ec44-4c2f-ac21-6b28f583695c\"},\"spec\":{\"progressDeadlineSeconds\":600,\"replicas\":1,\"revisionHistoryLimit\":10,\"selector\":{\"matchLabels\":{\"app\":\"admin-http2\",\"version\":\"v1\"}},\"strategy\":{\"rollingUpdate\":{\"maxSurge\":\"25%\",\"maxUnavailable\":\"25%\"},\"type\":\"RollingUpdate\"},\"template\":{\"metadata\":{\"annotations\":{\"kubesphere.io/restartedAt\":\"2022-06-03T11:58:47.575Z\"},\"creationTimestamp\":null,\"labels\":{\"app\":\"admin-http2\",\"version\":\"v1\"}},\"spec\":{\"containers\":[{\"envFrom\":[{\"configMapRef\":{\"name\":\"app-server-config\"}},{\"configMapRef\":{\"name\":\"admin-http-config\"}}],\"image\":\"harbor6.wns8.io/srqz/admin-http2:1.1.10\",\"imagePullPolicy\":\"IfNotPresent\",\"name\":\"container-myfd5b\",\"ports\":[{\"containerPort\":81,\"name\":\"tcp-81\",\"protocol\":\"TCP\"}],\"resources\":{},\"terminationMessagePath\":\"/dev/termination-log\",\"terminationMessagePolicy\":\"File\",\"volumeMounts\":[{\"mountPath\":\"/etc/srqz/\",\"name\":\"volume-7iym8i\",\"readOnly\":true}]}],\"dnsPolicy\":\"ClusterFirst\",\"restartPolicy\":\"Always\",\"schedulerName\":\"default-scheduler\",\"securityContext\":{},\"serviceAccount\":\"default\",\"serviceAccountName\":\"default\",\"terminationGracePeriodSeconds\":30,\"volumes\":[{\"configMap\":{\"defaultMode\":420,\"items\":[{\"key\":\"wrs_pub.pem\",\"path\":\"wrs_pub.pem\"}],\"name\":\"admin-http-config\"},\"name\":\"volume-7iym8i\"}]}}},\"status\":{\"availableReplicas\":1,\"conditions\":[{\"lastTransitionTime\":\"2022-04-15T22:40:32Z\",\"lastUpdateTime\":\"2022-06-13T09:00:20Z\",\"message\":\"ReplicaSet \\\"admin-http2-v1-587465958\\\" has successfully progressed.\",\"reason\":\"NewReplicaSetAvailable\",\"status\":\"True\",\"type\":\"Progressing\"},{\"lastTransitionTime\":\"2022-06-25T09:02:22Z\",\"lastUpdateTime\":\"2022-06-25T09:02:22Z\",\"message\":\"Deployment has minimum availability.\",\"reason\":\"MinimumReplicasAvailable\",\"status\":\"True\",\"type\":\"Available\"}],\"observedGeneration\":42,\"readyReplicas\":1,\"replicas\":1,\"updatedReplicas\":1}}\n"},"generation":48,"labels":{"app":"admin-http2","version":"v1"},"name":"admin-http2-v1","namespace":"srqz-bl003-admin"},"spec":{"progressDeadlineSeconds":600,"replicas":0,"revisionHistoryLimit":10,"selector":{"matchLabels":{"app":"admin-http2","version":"v1"}},"strategy":{"rollingUpdate":{"maxSurge":"25%","maxUnavailable":"25%"},"type":"RollingUpdate"},"template":{"metadata":{"annotations":{"kubesphere.io/restartedAt":"2022-06-03T11:58:47.575Z"},"creationTimestamp":null,"labels":{"app":"admin-http2","version":"v1"}},"spec":{"containers":[{"envFrom":[{"configMapRef":{"name":"app-server-config"}},{"configMapRef":{"name":"admin-http-config"}}],"image":"harbor62.wns8.io/srqz/admin-http2:1.1.16","imagePullPolicy":"IfNotPresent","name":"container-myfd5b","ports":[{"containerPort":81,"name":"tcp-81","protocol":"TCP"}],"resources":{},"terminationMessagePath":"/dev/termination-log","terminationMessagePolicy":"File","volumeMounts":[{"mountPath":"/etc/srqz/","name":"volume-7iym8i","readOnly":true}]}],"dnsPolicy":"ClusterFirst","restartPolicy":"Always","schedulerName":"default-scheduler","securityContext":{},"serviceAccount":"default","serviceAccountName":"default","terminationGracePeriodSeconds":30,"volumes":[{"configMap":{"defaultMode":420,"items":[{"key":"wrs_pub.pem","path":"wrs_pub.pem"}],"name":"admin-http-config"},"name":"volume-7iym8i"}]}}}}
{"apiVersion":"apps/v1","kind":"Deployment","metadata":{"annotations":{"deployment.kubernetes.io/revision":"34","kubectl.kubernetes.io/last-applied-configuration":"{\"apiVersion\":\"apps/v1\",\"kind\":\"Deployment\",\"metadata\":{\"annotations\":{\"deployment.kubernetes.io/revision\":\"24\",\"kubesphere.io/creator\":\"zhu\"},\"creationTimestamp\":\"2022-04-15T22:38:53Z\",\"generation\":25,\"labels\":{\"app\":\"admin-web-ui\",\"version\":\"v1\"},\"name\":\"admin-web-ui-v1\",\"namespace\":\"srqz-bl003-admin\",\"resourceVersion\":\"141293128\",\"uid\":\"6c1aee59-8a2f-44b0-a50d-729533a85c6e\"},\"spec\":{\"progressDeadlineSeconds\":600,\"replicas\":1,\"revisionHistoryLimit\":10,\"selector\":{\"matchLabels\":{\"app\":\"admin-web-ui\",\"version\":\"v1\"}},\"strategy\":{\"rollingUpdate\":{\"maxSurge\":\"25%\",\"maxUnavailable\":\"25%\"},\"type\":\"RollingUpdate\"},\"template\":{\"metadata\":{\"annotations\":{\"kubesphere.io/restartedAt\":\"2022-06-03T10:23:56.165Z\"},\"creationTimestamp\":null,\"labels\":{\"app\":\"admin-web-ui\",\"pod-template-hash\":\"6cdf5bffdc\",\"version\":\"v1\"}},\"spec\":{\"containers\":[{\"envFrom\":[{\"configMapRef\":{\"name\":\"admin-ui-config\"}}],\"image\":\"harbor6.wns8.io/srqz/admin-web-ui:1.1.10\",\"imagePullPolicy\":\"IfNotPresent\",\"name\":\"container-mure52\",\"ports\":[{\"containerPort\":80,\"name\":\"http-8080\",\"protocol\":\"TCP\"}],\"resources\":{},\"terminationMessagePath\":\"/dev/termination-log\",\"terminationMessagePolicy\":\"File\"}],\"dnsPolicy\":\"ClusterFirst\",\"restartPolicy\":\"Always\",\"schedulerName\":\"default-scheduler\",\"securityContext\":{},\"serviceAccount\":\"default\",\"serviceAccountName\":\"default\",\"terminationGracePeriodSeconds\":30}}},\"status\":{\"availableReplicas\":1,\"conditions\":[{\"lastTransitionTime\":\"2022-04-15T22:38:54Z\",\"lastUpdateTime\":\"2022-04-15T22:38:54Z\",\"message\":\"Deployment has minimum availability.\",\"reason\":\"MinimumReplicasAvailable\",\"status\":\"True\",\"type\":\"Available\"},{\"lastTransitionTime\":\"2022-04-15T22:38:53Z\",\"lastUpdateTime\":\"2022-06-13T09:00:08Z\",\"message\":\"ReplicaSet \\\"admin-web-ui-v1-5894645957\\\" has successfully progressed.\",\"reason\":\"NewReplicaSetAvailable\",\"status\":\"True\",\"type\":\"Progressing\"}],\"observedGeneration\":25,\"readyReplicas\":1,\"replicas\":1,\"updatedReplicas\":1}}\n"},"generation":37,"labels":{"app":"admin-web-ui","version":"v1"},"name":"admin-web-ui-v1","namespace":"srqz-bl003-admin"},"spec":{"progressDeadlineSeconds":600,"replicas":0,"revisionHistoryLimit":10,"selector":{"matchLabels":{"app":"admin-web-ui","version":"v1"}},"strategy":{"rollingUpdate":{"maxSurge":"25%","maxUnavailable":"25%"},"type":"RollingUpdate"},"template":{"metadata":{"annotations":{"kubesphere.io/restartedAt":"2022-07-27T05:06:19.438Z"},"creationTimestamp":null,"labels":{"app":"admin-web-ui","pod-template-hash":"6cdf5bffdc","version":"v1"}},"spec":{"containers":[{"envFrom":[{"configMapRef":{"name":"admin-ui-config"}}],"image":"harbor6.wns8.io/srqz/admin-web-ui:1.1.29","imagePullPolicy":"IfNotPresent","name":"container-mure52","ports":[{"containerPort":80,"name":"http-8080","protocol":"TCP"}],"resources":{},"terminationMessagePath":"/dev/termination-log","terminationMessagePolicy":"File"}],"dnsPolicy":"ClusterFirst","restartPolicy":"Always","schedulerName":"default-scheduler","securityContext":{},"serviceAccount":"default","serviceAccountName":"default","terminationGracePeriodSeconds":30}}}}
{"apiVersion":"apps/v1","kind":"Deployment","metadata":{"annotations":{"deployment.kubernetes.io/revision":"50","kubectl.kubernetes.io/last-applied-configuration":"{\"apiVersion\":\"apps/v1\",\"kind\":\"Deployment\",\"metadata\":{\"annotations\":{\"deployment.kubernetes.io/revision\":\"44\",\"kubesphere.io/creator\":\"admin\",\"servicemesh.kubesphere.io/enabled\":\"true\"},\"creationTimestamp\":\"2021-12-29T01:36:25Z\",\"generation\":45,\"labels\":{\"app\":\"app-lottery-shaker-service\",\"app.kubernetes.io/name\":\"srqz-admin\",\"app.kubernetes.io/version\":\"v1\",\"version\":\"v1\"},\"name\":\"app-lottery-shaker-service-v1\",\"namespace\":\"srqz-bl003-admin\",\"resourceVersion\":\"141293130\",\"uid\":\"f4e68e2c-cfcc-41f1-9363-59a09175627d\"},\"spec\":{\"progressDeadlineSeconds\":600,\"replicas\":1,\"revisionHistoryLimit\":10,\"selector\":{\"matchLabels\":{\"app\":\"app-lottery-shaker-service\",\"app.kubernetes.io/name\":\"srqz-admin\",\"app.kubernetes.io/version\":\"v1\",\"version\":\"v1\"}},\"strategy\":{\"rollingUpdate\":{\"maxSurge\":\"25%\",\"maxUnavailable\":\"25%\"},\"type\":\"RollingUpdate\"},\"template\":{\"metadata\":{\"annotations\":{\"kubesphere.io/restartedAt\":\"2022-06-17T03:45:46.364Z\",\"sidecar.istio.io/inject\":\"true\"},\"creationTimestamp\":null,\"labels\":{\"app\":\"app-lottery-shaker-service\",\"app.kubernetes.io/name\":\"srqz-admin\",\"app.kubernetes.io/version\":\"v1\",\"pod-template-hash\":\"74c64898dd\",\"version\":\"v1\"}},\"spec\":{\"affinity\":{},\"containers\":[{\"env\":[{\"name\":\"NLOG.level\",\"value\":\"debug\"}],\"envFrom\":[{\"configMapRef\":{\"name\":\"app-server-config\"}}],\"image\":\"harbor6.wns8.io/srqz/app-lottery-shaker-service:1.1.66\",\"imagePullPolicy\":\"IfNotPresent\",\"name\":\"container-cw7bgz\",\"ports\":[{\"containerPort\":8080,\"name\":\"http-80\",\"protocol\":\"TCP\"}],\"resources\":{},\"terminationMessagePath\":\"/dev/termination-log\",\"terminationMessagePolicy\":\"File\"}],\"dnsPolicy\":\"ClusterFirst\",\"restartPolicy\":\"Always\",\"schedulerName\":\"default-scheduler\",\"securityContext\":{},\"serviceAccount\":\"default\",\"serviceAccountName\":\"default\",\"terminationGracePeriodSeconds\":30}}},\"status\":{\"availableReplicas\":1,\"conditions\":[{\"lastTransitionTime\":\"2022-04-07T09:02:17Z\",\"lastUpdateTime\":\"2022-04-07T09:02:17Z\",\"message\":\"Deployment has minimum availability.\",\"reason\":\"MinimumReplicasAvailable\",\"status\":\"True\",\"type\":\"Available\"},{\"lastTransitionTime\":\"2021-12-29T01:36:25Z\",\"lastUpdateTime\":\"2022-06-17T03:45:50Z\",\"message\":\"ReplicaSet \\\"app-lottery-shaker-service-v1-5b4c4c9b46\\\" has successfully progressed.\",\"reason\":\"NewReplicaSetAvailable\",\"status\":\"True\",\"type\":\"Progressing\"}],\"observedGeneration\":45,\"readyReplicas\":1,\"replicas\":1,\"updatedReplicas\":1}}\n","servicemesh.kubesphere.io/enabled":"true"},"generation":55,"labels":{"app":"app-lottery-shaker-service","app.kubernetes.io/name":"srqz-admin","app.kubernetes.io/version":"v1","version":"v1"},"name":"app-lottery-shaker-service-v1","namespace":"srqz-bl003-admin"},"spec":{"progressDeadlineSeconds":600,"replicas":0,"revisionHistoryLimit":10,"selector":{"matchLabels":{"app":"app-lottery-shaker-service","app.kubernetes.io/name":"srqz-admin","app.kubernetes.io/version":"v1","version":"v1"}},"strategy":{"rollingUpdate":{"maxSurge":"25%","maxUnavailable":"25%"},"type":"RollingUpdate"},"template":{"metadata":{"annotations":{"kubesphere.io/restartedAt":"2023-04-23T06:25:28.094Z","sidecar.istio.io/inject":"true"},"creationTimestamp":null,"labels":{"app":"app-lottery-shaker-service","app.kubernetes.io/name":"srqz-admin","app.kubernetes.io/version":"v1","pod-template-hash":"74c64898dd","version":"v1"}},"spec":{"affinity":{},"containers":[{"env":[{"name":"NLOG.level","value":"debug"}],"envFrom":[{"configMapRef":{"name":"app-server-config"}}],"image":"harbor6.wns8.io/srqz/app-lottery-shaker-service:1.1.72.1","imagePullPolicy":"IfNotPresent","name":"container-cw7bgz","ports":[{"containerPort":8080,"name":"http-80","protocol":"TCP"}],"resources":{},"terminationMessagePath":"/dev/termination-log","terminationMessagePolicy":"File"}],"dnsPolicy":"ClusterFirst","restartPolicy":"Always","schedulerName":"default-scheduler","securityContext":{},"serviceAccount":"default","serviceAccountName":"default","terminationGracePeriodSeconds":30}}}}
{"apiVersion":"apps/v1","kind":"Deployment","metadata":{"annotations":{"deployment.kubernetes.io/revision":"15","kubectl.kubernetes.io/last-applied-configuration":"{\"apiVersion\":\"apps/v1\",\"kind\":\"Deployment\",\"metadata\":{\"annotations\":{\"deployment.kubernetes.io/revision\":\"15\",\"kubesphere.io/creator\":\"admin\",\"servicemesh.kubesphere.io/enabled\":\"true\"},\"creationTimestamp\":\"2021-12-29T01:46:33Z\",\"generation\":32,\"labels\":{\"app\":\"cas-server\",\"app.kubernetes.io/name\":\"srqz-admin\",\"app.kubernetes.io/version\":\"v1\",\"version\":\"v1\"},\"name\":\"cas-server-v1\",\"namespace\":\"srqz-bl003-admin\",\"resourceVersion\":\"141293132\",\"uid\":\"5ffffbc2-152e-4ee7-8127-fc3f59b7b1d1\"},\"spec\":{\"progressDeadlineSeconds\":600,\"replicas\":1,\"revisionHistoryLimit\":10,\"selector\":{\"matchLabels\":{\"app\":\"cas-server\",\"app.kubernetes.io/name\":\"srqz-admin\",\"app.kubernetes.io/version\":\"v1\",\"version\":\"v1\"}},\"strategy\":{\"type\":\"Recreate\"},\"template\":{\"metadata\":{\"annotations\":{\"kubesphere.io/restartedAt\":\"2022-06-03T11:27:37.295Z\",\"logging.kubesphere.io/logsidecar-config\":\"{}\",\"sidecar.istio.io/inject\":\"true\"},\"creationTimestamp\":null,\"labels\":{\"app\":\"cas-server\",\"app.kubernetes.io/name\":\"srqz-admin\",\"app.kubernetes.io/version\":\"v1\",\"pod-template-hash\":\"6648bb5489\",\"version\":\"v1\"}},\"spec\":{\"affinity\":{\"podAntiAffinity\":{\"preferredDuringSchedulingIgnoredDuringExecution\":[{\"podAffinityTerm\":{\"labelSelector\":{\"matchLabels\":{\"app\":\"cas-server\",\"app.kubernetes.io/name\":\"srqz\",\"app.kubernetes.io/version\":\"v1\",\"version\":\"v1\"}},\"topologyKey\":\"kubernetes.io/hostname\"},\"weight\":100}]}},\"containers\":[{\"command\":[\"/entrypoint.sh\"],\"env\":[{\"name\":\"CAS_WAR\",\"value\":\"cas.war\"},{\"name\":\"CAS_SPRING_PROFILES\",\"value\":\"standalone\"},{\"name\":\"MAX_HEAP_OPT\",\"value\":\"-Xmx2G\"},{\"name\":\"JAVA_ENABLE_DEBUG\",\"value\":\"true\"},{\"name\":\"JAVA_DEBUG_SUSPEND\",\"value\":\"n\"},{\"name\":\"KUBERNETES_NAMESPACE\",\"value\":\"cas\"},{\"name\":\"POD_IP\",\"valueFrom\":{\"fieldRef\":{\"apiVersion\":\"v1\",\"fieldPath\":\"status.podIP\"}}}],\"image\":\"harbor6.wns8.io/srqz/cas-server-http:6.4.5\",\"imagePullPolicy\":\"IfNotPresent\",\"name\":\"container-n3olrq\",\"ports\":[{\"containerPort\":8080,\"name\":\"http-8080\",\"protocol\":\"TCP\"},{\"containerPort\":5005,\"name\":\"jvm-debug\",\"protocol\":\"TCP\"}],\"resources\":{},\"terminationMessagePath\":\"/dev/termination-log\",\"terminationMessagePolicy\":\"File\",\"volumeMounts\":[{\"mountPath\":\"/var/cas\",\"name\":\"data\"},{\"mountPath\":\"/etc/cas/config/cas.properties\",\"name\":\"cas-config-cas-properties\",\"subPath\":\"cas.properties\"},{\"mountPath\":\"/etc/cas/config/cas.yaml\",\"name\":\"cas-config-cas-yaml\",\"subPath\":\"cas.yaml\"},{\"mountPath\":\"/entrypoint.sh\",\"name\":\"scripts\",\"subPath\":\"entrypoint.sh\"},{\"mountPath\":\"/var/log\",\"name\":\"logdir\"},{\"mountPath\":\"/etc/cas/thekeystore\",\"name\":\"cas-server-keystore\",\"subPath\":\"thekeystore\"},{\"mountPath\":\"/etc/cas/truststore\",\"name\":\"truststore\",\"subPath\":\"truststore\"},{\"mountPath\":\"/etc/cas/services/\",\"name\":\"volume-unqou7\",\"readOnly\":true}]}],\"dnsPolicy\":\"ClusterFirst\",\"restartPolicy\":\"Always\",\"schedulerName\":\"default-scheduler\",\"securityContext\":{\"fsGroup\":1000},\"serviceAccount\":\"default\",\"serviceAccountName\":\"default\",\"terminationGracePeriodSeconds\":30,\"volumes\":[{\"name\":\"data\",\"persistentVolumeClaim\":{\"claimName\":\"data-cas-server-0\"}},{\"configMap\":{\"defaultMode\":420,\"name\":\"cas-server-casconfig\"},\"name\":\"cas-config-cas-properties\"},{\"configMap\":{\"defaultMode\":420,\"name\":\"cas-server-casconfig\"},\"name\":\"cas-config-cas-yaml\"},{\"configMap\":{\"defaultMode\":493,\"name\":\"cas-server-scripts\"},\"name\":\"scripts\"},{\"emptyDir\":{},\"name\":\"logdir\"},{\"name\":\"cas-server-keystore\",\"secret\":{\"defaultMode\":292,\"items\":[{\"key\":\"thekeystore\",\"path\":\"thekeystore\"}],\"secretName\":\"cas-server-keystore\"}},{\"configMap\":{\"defaultMode\":292,\"name\":\"cas-truststore\"},\"name\":\"truststore\"},{\"configMap\":{\"defaultMode\":420,\"items\":[{\"key\":\"2\",\"path\":\"2.json\"}],\"name\":\"cas-service-config\"},\"name\":\"volume-unqou7\"}]}}},\"status\":{\"availableReplicas\":1,\"conditions\":[{\"lastTransitionTime\":\"2022-06-03T12:19:57Z\",\"lastUpdateTime\":\"2022-06-03T12:19:57Z\",\"message\":\"Deployment has minimum availability.\",\"reason\":\"MinimumReplicasAvailable\",\"status\":\"True\",\"type\":\"Available\"},{\"lastTransitionTime\":\"2022-04-13T15:10:59Z\",\"lastUpdateTime\":\"2022-06-03T12:19:57Z\",\"message\":\"ReplicaSet \\\"cas-server-v1-6d4765f7f7\\\" has successfully progressed.\",\"reason\":\"NewReplicaSetAvailable\",\"status\":\"True\",\"type\":\"Progressing\"}],\"observedGeneration\":32,\"readyReplicas\":1,\"replicas\":1,\"updatedReplicas\":1}}\n","servicemesh.kubesphere.io/enabled":"true"},"generation":34,"labels":{"app":"cas-server","app.kubernetes.io/name":"srqz-admin","app.kubernetes.io/version":"v1","version":"v1"},"name":"cas-server-v1","namespace":"srqz-bl003-admin"},"spec":{"progressDeadlineSeconds":600,"replicas":0,"revisionHistoryLimit":10,"selector":{"matchLabels":{"app":"cas-server","app.kubernetes.io/name":"srqz-admin","app.kubernetes.io/version":"v1","version":"v1"}},"strategy":{"type":"Recreate"},"template":{"metadata":{"annotations":{"kubesphere.io/restartedAt":"2022-06-03T11:27:37.295Z","logging.kubesphere.io/logsidecar-config":"{}","sidecar.istio.io/inject":"true"},"creationTimestamp":null,"labels":{"app":"cas-server","app.kubernetes.io/name":"srqz-admin","app.kubernetes.io/version":"v1","pod-template-hash":"6648bb5489","version":"v1"}},"spec":{"affinity":{"podAntiAffinity":{"preferredDuringSchedulingIgnoredDuringExecution":[{"podAffinityTerm":{"labelSelector":{"matchLabels":{"app":"cas-server","app.kubernetes.io/name":"srqz","app.kubernetes.io/version":"v1","version":"v1"}},"topologyKey":"kubernetes.io/hostname"},"weight":100}]}},"containers":[{"command":["/entrypoint.sh"],"env":[{"name":"CAS_WAR","value":"cas.war"},{"name":"CAS_SPRING_PROFILES","value":"standalone"},{"name":"MAX_HEAP_OPT","value":"-Xmx2G"},{"name":"JAVA_ENABLE_DEBUG","value":"true"},{"name":"JAVA_DEBUG_SUSPEND","value":"n"},{"name":"KUBERNETES_NAMESPACE","value":"cas"},{"name":"POD_IP","valueFrom":{"fieldRef":{"apiVersion":"v1","fieldPath":"status.podIP"}}}],"image":"harbor6.wns8.io/srqz/cas-server-http:6.4.5","imagePullPolicy":"IfNotPresent","name":"container-n3olrq","ports":[{"containerPort":8080,"name":"http-8080","protocol":"TCP"},{"containerPort":5005,"name":"jvm-debug","protocol":"TCP"}],"resources":{},"terminationMessagePath":"/dev/termination-log","terminationMessagePolicy":"File","volumeMounts":[{"mountPath":"/var/cas","name":"data"},{"mountPath":"/etc/cas/config/cas.properties","name":"cas-config-cas-properties","subPath":"cas.properties"},{"mountPath":"/etc/cas/config/cas.yaml","name":"cas-config-cas-yaml","subPath":"cas.yaml"},{"mountPath":"/entrypoint.sh","name":"scripts","subPath":"entrypoint.sh"},{"mountPath":"/var/log","name":"logdir"},{"mountPath":"/etc/cas/thekeystore","name":"cas-server-keystore","subPath":"thekeystore"},{"mountPath":"/etc/cas/truststore","name":"truststore","subPath":"truststore"},{"mountPath":"/etc/cas/services/","name":"volume-unqou7","readOnly":true}]}],"dnsPolicy":"ClusterFirst","restartPolicy":"Always","schedulerName":"default-scheduler","securityContext":{"fsGroup":1000},"serviceAccount":"default","serviceAccountName":"default","terminationGracePeriodSeconds":30,"volumes":[{"name":"data","persistentVolumeClaim":{"claimName":"data-cas-server-0"}},{"configMap":{"defaultMode":420,"name":"cas-server-casconfig"},"name":"cas-config-cas-properties"},{"configMap":{"defaultMode":420,"name":"cas-server-casconfig"},"name":"cas-config-cas-yaml"},{"configMap":{"defaultMode":493,"name":"cas-server-scripts"},"name":"scripts"},{"emptyDir":{},"name":"logdir"},{"name":"cas-server-keystore","secret":{"defaultMode":292,"items":[{"key":"thekeystore","path":"thekeystore"}],"secretName":"cas-server-keystore"}},{"configMap":{"defaultMode":292,"name":"cas-truststore"},"name":"truststore"},{"configMap":{"defaultMode":420,"items":[{"key":"2","path":"2.json"}],"name":"cas-service-config"},"name":"volume-unqou7"}]}}}}
{"apiVersion":"apps/v1","kind":"Deployment","metadata":{"annotations":{"deployment.kubernetes.io/revision":"3","kubectl.kubernetes.io/last-applied-configuration":"{\"apiVersion\":\"apps/v1\",\"kind\":\"Deployment\",\"metadata\":{\"annotations\":{\"deployment.kubernetes.io/revision\":\"2\",\"kubesphere.io/creator\":\"zhu\"},\"creationTimestamp\":\"2022-04-15T22:14:05Z\",\"generation\":3,\"labels\":{\"app\":\"data-cleaner\",\"version\":\"v1\"},\"name\":\"data-cleaner-v1\",\"namespace\":\"srqz-bl003-admin\",\"resourceVersion\":\"141293134\",\"uid\":\"b28509b1-e8ad-440c-9db0-f3ee28707088\"},\"spec\":{\"progressDeadlineSeconds\":600,\"replicas\":1,\"revisionHistoryLimit\":10,\"selector\":{\"matchLabels\":{\"app\":\"data-cleaner\",\"version\":\"v1\"}},\"strategy\":{\"rollingUpdate\":{\"maxSurge\":\"25%\",\"maxUnavailable\":\"25%\"},\"type\":\"RollingUpdate\"},\"template\":{\"metadata\":{\"annotations\":{\"logging.kubesphere.io/logsidecar-config\":\"{}\"},\"creationTimestamp\":null,\"labels\":{\"app\":\"data-cleaner\",\"version\":\"v1\"}},\"spec\":{\"containers\":[{\"envFrom\":[{\"configMapRef\":{\"name\":\"app-server-config\"}},{\"configMapRef\":{\"name\":\"data-cleaner-config\"}}],\"image\":\"harbor6.wns8.io/srqz/data_cleaner:1.0.4\",\"imagePullPolicy\":\"IfNotPresent\",\"name\":\"container-d5np26\",\"ports\":[{\"containerPort\":8081,\"name\":\"tcp-8081\",\"protocol\":\"TCP\"}],\"resources\":{},\"terminationMessagePath\":\"/dev/termination-log\",\"terminationMessagePolicy\":\"File\",\"volumeMounts\":[{\"mountPath\":\"/data-cleaner-data\",\"name\":\"volume-9zvv09\"}]}],\"dnsPolicy\":\"ClusterFirst\",\"restartPolicy\":\"Always\",\"schedulerName\":\"default-scheduler\",\"securityContext\":{},\"serviceAccount\":\"default\",\"serviceAccountName\":\"default\",\"terminationGracePeriodSeconds\":30,\"volumes\":[{\"name\":\"volume-9zvv09\",\"persistentVolumeClaim\":{\"claimName\":\"data-cleaner-backup\"}}]}}},\"status\":{\"availableReplicas\":1,\"conditions\":[{\"lastTransitionTime\":\"2022-04-15T22:14:17Z\",\"lastUpdateTime\":\"2022-04-15T22:14:17Z\",\"message\":\"Deployment has minimum availability.\",\"reason\":\"MinimumReplicasAvailable\",\"status\":\"True\",\"type\":\"Available\"},{\"lastTransitionTime\":\"2022-04-15T22:14:05Z\",\"lastUpdateTime\":\"2022-04-15T22:14:33Z\",\"message\":\"ReplicaSet \\\"data-cleaner-v1-b4c75c8c4\\\" has successfully progressed.\",\"reason\":\"NewReplicaSetAvailable\",\"status\":\"True\",\"type\":\"Progressing\"}],\"observedGeneration\":3,\"readyReplicas\":1,\"replicas\":1,\"updatedReplicas\":1}}\n"},"generation":6,"labels":{"app":"data-cleaner","version":"v1"},"name":"data-cleaner-v1","namespace":"srqz-bl003-admin"},"spec":{"progressDeadlineSeconds":600,"replicas":0,"revisionHistoryLimit":10,"selector":{"matchLabels":{"app":"data-cleaner","version":"v1"}},"strategy":{"rollingUpdate":{"maxSurge":"25%","maxUnavailable":"25%"},"type":"RollingUpdate"},"template":{"metadata":{"annotations":{"logging.kubesphere.io/logsidecar-config":"{}"},"creationTimestamp":null,"labels":{"app":"data-cleaner","version":"v1"}},"spec":{"containers":[{"envFrom":[{"configMapRef":{"name":"app-server-config"}},{"configMapRef":{"name":"data-cleaner-config"}}],"image":"harbor62.wns8.io/srqz/data_cleaner:1.0.4","imagePullPolicy":"IfNotPresent","name":"container-d5np26","ports":[{"containerPort":8081,"name":"tcp-8081","protocol":"TCP"}],"resources":{},"terminationMessagePath":"/dev/termination-log","terminationMessagePolicy":"File","volumeMounts":[{"mountPath":"/data-cleaner-data","name":"volume-9zvv09"}]}],"dnsPolicy":"ClusterFirst","restartPolicy":"Always","schedulerName":"default-scheduler","securityContext":{},"serviceAccount":"default","serviceAccountName":"default","terminationGracePeriodSeconds":30,"volumes":[{"name":"volume-9zvv09","persistentVolumeClaim":{"claimName":"data-cleaner-backup"}}]}}}}
{"apiVersion":"apps/v1","kind":"Deployment","metadata":{"annotations":{"deployment.kubernetes.io/revision":"17","kubectl.kubernetes.io/last-applied-configuration":"{\"apiVersion\":\"apps/v1\",\"kind\":\"Deployment\",\"metadata\":{\"annotations\":{\"deployment.kubernetes.io/revision\":\"16\",\"kubesphere.io/creator\":\"admin\"},\"creationTimestamp\":\"2022-01-13T21:12:50Z\",\"generation\":17,\"labels\":{\"app\":\"game-amount-transfer-service\"},\"name\":\"game-amount-transfer-service\",\"namespace\":\"srqz-bl003-admin\",\"resourceVersion\":\"141293136\",\"uid\":\"e1cc554f-c003-4c65-887a-9d614cbebf63\"},\"spec\":{\"progressDeadlineSeconds\":600,\"replicas\":1,\"revisionHistoryLimit\":10,\"selector\":{\"matchLabels\":{\"app\":\"game-amount-transfer-service\"}},\"strategy\":{\"rollingUpdate\":{\"maxSurge\":\"25%\",\"maxUnavailable\":\"25%\"},\"type\":\"RollingUpdate\"},\"template\":{\"metadata\":{\"annotations\":{\"kubesphere.io/restartedAt\":\"2022-04-13T15:10:36.397Z\"},\"creationTimestamp\":null,\"labels\":{\"app\":\"game-amount-transfer-service\"}},\"spec\":{\"affinity\":{\"nodeAffinity\":{\"requiredDuringSchedulingIgnoredDuringExecution\":{\"nodeSelectorTerms\":[{\"matchExpressions\":[{\"key\":\"apiwhite\",\"operator\":\"In\",\"values\":[\"1\"]}]}]}}},\"containers\":[{\"envFrom\":[{\"configMapRef\":{\"name\":\"app-server-config\"}},{\"configMapRef\":{\"name\":\"game-record-sync-service-config\"}}],\"image\":\"harbor6.wns8.io/srqz/game-amount-transfer-service:1.0.37\",\"imagePullPolicy\":\"IfNotPresent\",\"name\":\"container-x9r7ni\",\"ports\":[{\"containerPort\":10002,\"name\":\"tcp-10002\",\"protocol\":\"TCP\"}],\"resources\":{},\"terminationMessagePath\":\"/dev/termination-log\",\"terminationMessagePolicy\":\"File\",\"volumeMounts\":[{\"mountPath\":\"/etc/keystore/rabbitmq.p12\",\"name\":\"lottery-admin-http-rabbitmq-ssl\",\"subPath\":\"rabbitmq.p12\"},{\"mountPath\":\"/etc/keystore/rabbitstore.jks\",\"name\":\"lottery-admin-http-rabbitmq-ssl\",\"subPath\":\"rabbitmq.jks\"}]}],\"dnsPolicy\":\"ClusterFirst\",\"restartPolicy\":\"Always\",\"schedulerName\":\"default-scheduler\",\"securityContext\":{},\"serviceAccount\":\"default\",\"serviceAccountName\":\"default\",\"terminationGracePeriodSeconds\":30,\"volumes\":[{\"configMap\":{\"defaultMode\":292,\"name\":\"rabbitmq-ssl\"},\"name\":\"lottery-admin-http-rabbitmq-ssl\"}]}}},\"status\":{\"availableReplicas\":1,\"conditions\":[{\"lastTransitionTime\":\"2022-01-13T21:12:50Z\",\"lastUpdateTime\":\"2022-04-16T03:05:05Z\",\"message\":\"ReplicaSet \\\"game-amount-transfer-service-fd478c545\\\" has successfully progressed.\",\"reason\":\"NewReplicaSetAvailable\",\"status\":\"True\",\"type\":\"Progressing\"},{\"lastTransitionTime\":\"2022-05-28T05:57:42Z\",\"lastUpdateTime\":\"2022-05-28T05:57:42Z\",\"message\":\"Deployment has minimum availability.\",\"reason\":\"MinimumReplicasAvailable\",\"status\":\"True\",\"type\":\"Available\"}],\"observedGeneration\":17,\"readyReplicas\":1,\"replicas\":1,\"updatedReplicas\":1}}\n"},"generation":20,"labels":{"app":"game-amount-transfer-service"},"name":"game-amount-transfer-service","namespace":"srqz-bl003-admin"},"spec":{"progressDeadlineSeconds":600,"replicas":0,"revisionHistoryLimit":10,"selector":{"matchLabels":{"app":"game-amount-transfer-service"}},"strategy":{"rollingUpdate":{"maxSurge":"25%","maxUnavailable":"25%"},"type":"RollingUpdate"},"template":{"metadata":{"annotations":{"kubesphere.io/restartedAt":"2022-04-13T15:10:36.397Z"},"creationTimestamp":null,"labels":{"app":"game-amount-transfer-service"}},"spec":{"affinity":{"nodeAffinity":{"requiredDuringSchedulingIgnoredDuringExecution":{"nodeSelectorTerms":[{"matchExpressions":[{"key":"apiwhite","operator":"In","values":["1"]}]}]}}},"containers":[{"envFrom":[{"configMapRef":{"name":"app-server-config"}},{"configMapRef":{"name":"game-record-sync-service-config"}}],"image":"harbor62.wns8.io/srqz/game-amount-transfer-service:1.0.37","imagePullPolicy":"IfNotPresent","name":"container-x9r7ni","ports":[{"containerPort":10002,"name":"tcp-10002","protocol":"TCP"}],"resources":{},"terminationMessagePath":"/dev/termination-log","terminationMessagePolicy":"File","volumeMounts":[{"mountPath":"/etc/keystore/rabbitmq.p12","name":"lottery-admin-http-rabbitmq-ssl","subPath":"rabbitmq.p12"},{"mountPath":"/etc/keystore/rabbitstore.jks","name":"lottery-admin-http-rabbitmq-ssl","subPath":"rabbitmq.jks"}]}],"dnsPolicy":"ClusterFirst","restartPolicy":"Always","schedulerName":"default-scheduler","securityContext":{},"serviceAccount":"default","serviceAccountName":"default","terminationGracePeriodSeconds":30,"volumes":[{"configMap":{"defaultMode":292,"name":"rabbitmq-ssl"},"name":"lottery-admin-http-rabbitmq-ssl"}]}}}}
{"apiVersion":"apps/v1","kind":"Deployment","metadata":{"annotations":{"deployment.kubernetes.io/revision":"29","kubectl.kubernetes.io/last-applied-configuration":"{\"apiVersion\":\"apps/v1\",\"kind\":\"Deployment\",\"metadata\":{\"annotations\":{\"deployment.kubernetes.io/revision\":\"28\",\"kubesphere.io/creator\":\"admin\",\"servicemesh.kubesphere.io/enabled\":\"true\"},\"creationTimestamp\":\"2021-12-29T01:19:41Z\",\"generation\":30,\"labels\":{\"app\":\"game-record-sync-service\",\"app.kubernetes.io/name\":\"srqz-admin\",\"app.kubernetes.io/version\":\"v1\",\"version\":\"v1\"},\"name\":\"game-record-sync-service-v1\",\"namespace\":\"srqz-bl003-admin\",\"resourceVersion\":\"141293139\",\"uid\":\"d2cbb692-b683-4cd4-9cdc-b3c273894680\"},\"spec\":{\"progressDeadlineSeconds\":600,\"replicas\":1,\"revisionHistoryLimit\":10,\"selector\":{\"matchLabels\":{\"app\":\"game-record-sync-service\",\"app.kubernetes.io/name\":\"srqz-admin\",\"app.kubernetes.io/version\":\"v1\",\"version\":\"v1\"}},\"strategy\":{\"rollingUpdate\":{\"maxSurge\":\"25%\",\"maxUnavailable\":\"25%\"},\"type\":\"RollingUpdate\"},\"template\":{\"metadata\":{\"annotations\":{\"kubesphere.io/restartedAt\":\"2022-02-08T23:36:08.647Z\",\"sidecar.istio.io/inject\":\"true\"},\"creationTimestamp\":null,\"labels\":{\"app\":\"game-record-sync-service\",\"app.kubernetes.io/name\":\"srqz-admin\",\"app.kubernetes.io/version\":\"v1\",\"version\":\"v1\"}},\"spec\":{\"affinity\":{\"nodeAffinity\":{\"requiredDuringSchedulingIgnoredDuringExecution\":{\"nodeSelectorTerms\":[{\"matchExpressions\":[{\"key\":\"apiwhite\",\"operator\":\"In\",\"values\":[\"1\"]}]}]}}},\"containers\":[{\"envFrom\":[{\"configMapRef\":{\"name\":\"app-server-config\"}},{\"configMapRef\":{\"name\":\"game-record-sync-service-config\"}}],\"image\":\"harbor6.wns8.io/srqz/game-record-sync-service:1.0.36\",\"imagePullPolicy\":\"IfNotPresent\",\"livenessProbe\":{\"failureThreshold\":3,\"httpGet\":{\"path\":\"/actuator/prometheus\",\"port\":10002,\"scheme\":\"HTTP\"},\"initialDelaySeconds\":10,\"periodSeconds\":5,\"successThreshold\":1,\"timeoutSeconds\":2},\"name\":\"container-mqozk5\",\"ports\":[{\"containerPort\":10002,\"name\":\"http-10002\",\"protocol\":\"TCP\"}],\"resources\":{},\"terminationMessagePath\":\"/dev/termination-log\",\"terminationMessagePolicy\":\"File\",\"volumeMounts\":[{\"mountPath\":\"/etc/keystore/rabbitmq.p12\",\"name\":\"lottery-admin-http-rabbitmq-ssl\",\"subPath\":\"rabbitmq.p12\"},{\"mountPath\":\"/etc/keystore/rabbitstore.jks\",\"name\":\"lottery-admin-http-rabbitmq-ssl\",\"subPath\":\"rabbitmq.jks\"}]}],\"dnsPolicy\":\"ClusterFirst\",\"restartPolicy\":\"Always\",\"schedulerName\":\"default-scheduler\",\"securityContext\":{},\"serviceAccount\":\"default\",\"serviceAccountName\":\"default\",\"terminationGracePeriodSeconds\":30,\"volumes\":[{\"configMap\":{\"defaultMode\":292,\"name\":\"rabbitmq-ssl\"},\"name\":\"lottery-admin-http-rabbitmq-ssl\"}]}}},\"status\":{\"availableReplicas\":1,\"conditions\":[{\"lastTransitionTime\":\"2021-12-29T01:19:41Z\",\"lastUpdateTime\":\"2022-04-17T21:49:35Z\",\"message\":\"ReplicaSet \\\"game-record-sync-service-v1-68768486b9\\\" has successfully progressed.\",\"reason\":\"NewReplicaSetAvailable\",\"status\":\"True\",\"type\":\"Progressing\"},{\"lastTransitionTime\":\"2022-05-28T06:04:31Z\",\"lastUpdateTime\":\"2022-05-28T06:04:31Z\",\"message\":\"Deployment has minimum availability.\",\"reason\":\"MinimumReplicasAvailable\",\"status\":\"True\",\"type\":\"Available\"}],\"observedGeneration\":30,\"readyReplicas\":1,\"replicas\":1,\"updatedReplicas\":1}}\n","servicemesh.kubesphere.io/enabled":"true"},"generation":33,"labels":{"app":"game-record-sync-service","app.kubernetes.io/name":"srqz-admin","app.kubernetes.io/version":"v1","version":"v1"},"name":"game-record-sync-service-v1","namespace":"srqz-bl003-admin"},"spec":{"progressDeadlineSeconds":600,"replicas":0,"revisionHistoryLimit":10,"selector":{"matchLabels":{"app":"game-record-sync-service","app.kubernetes.io/name":"srqz-admin","app.kubernetes.io/version":"v1","version":"v1"}},"strategy":{"rollingUpdate":{"maxSurge":"25%","maxUnavailable":"25%"},"type":"RollingUpdate"},"template":{"metadata":{"annotations":{"kubesphere.io/restartedAt":"2022-02-08T23:36:08.647Z","sidecar.istio.io/inject":"true"},"creationTimestamp":null,"labels":{"app":"game-record-sync-service","app.kubernetes.io/name":"srqz-admin","app.kubernetes.io/version":"v1","version":"v1"}},"spec":{"affinity":{"nodeAffinity":{"requiredDuringSchedulingIgnoredDuringExecution":{"nodeSelectorTerms":[{"matchExpressions":[{"key":"apiwhite","operator":"In","values":["1"]}]}]}}},"containers":[{"envFrom":[{"configMapRef":{"name":"app-server-config"}},{"configMapRef":{"name":"game-record-sync-service-config"}}],"image":"harbor62.wns8.io/srqz/game-record-sync-service:1.0.36","imagePullPolicy":"IfNotPresent","livenessProbe":{"failureThreshold":3,"httpGet":{"path":"/actuator/prometheus","port":10002,"scheme":"HTTP"},"initialDelaySeconds":10,"periodSeconds":5,"successThreshold":1,"timeoutSeconds":2},"name":"container-mqozk5","ports":[{"containerPort":10002,"name":"http-10002","protocol":"TCP"}],"resources":{},"terminationMessagePath":"/dev/termination-log","terminationMessagePolicy":"File","volumeMounts":[{"mountPath":"/etc/keystore/rabbitmq.p12","name":"lottery-admin-http-rabbitmq-ssl","subPath":"rabbitmq.p12"},{"mountPath":"/etc/keystore/rabbitstore.jks","name":"lottery-admin-http-rabbitmq-ssl","subPath":"rabbitmq.jks"}]}],"dnsPolicy":"ClusterFirst","restartPolicy":"Always","schedulerName":"default-scheduler","securityContext":{},"serviceAccount":"default","serviceAccountName":"default","terminationGracePeriodSeconds":30,"volumes":[{"configMap":{"defaultMode":292,"name":"rabbitmq-ssl"},"name":"lottery-admin-http-rabbitmq-ssl"}]}}}}
{"apiVersion":"apps/v1","kind":"Deployment","metadata":{"annotations":{"deployment.kubernetes.io/revision":"7","kubectl.kubernetes.io/last-applied-configuration":"{\"apiVersion\":\"apps/v1\",\"kind\":\"Deployment\",\"metadata\":{\"annotations\":{\"deployment.kubernetes.io/revision\":\"6\",\"kubesphere.io/creator\":\"admin\",\"servicemesh.kubesphere.io/enabled\":\"true\"},\"creationTimestamp\":\"2021-12-29T01:03:13Z\",\"generation\":7,\"labels\":{\"app\":\"lottery-admin-http-ui\",\"app.kubernetes.io/name\":\"srqz-admin\",\"app.kubernetes.io/version\":\"v1\",\"version\":\"v1\"},\"name\":\"lottery-admin-http-ui-v1\",\"namespace\":\"srqz-bl003-admin\",\"resourceVersion\":\"141293141\",\"uid\":\"42e1cf48-d791-4ace-98b1-251f406530e9\"},\"spec\":{\"progressDeadlineSeconds\":600,\"replicas\":1,\"revisionHistoryLimit\":10,\"selector\":{\"matchLabels\":{\"app\":\"lottery-admin-http-ui\",\"app.kubernetes.io/name\":\"srqz-admin\",\"app.kubernetes.io/version\":\"v1\",\"version\":\"v1\"}},\"strategy\":{\"rollingUpdate\":{\"maxSurge\":\"25%\",\"maxUnavailable\":\"25%\"},\"type\":\"RollingUpdate\"},\"template\":{\"metadata\":{\"annotations\":{\"kubesphere.io/restartedAt\":\"2022-06-03T10:37:46.484Z\",\"sidecar.istio.io/inject\":\"true\"},\"creationTimestamp\":null,\"labels\":{\"app\":\"lottery-admin-http-ui\",\"app.kubernetes.io/name\":\"srqz-admin\",\"app.kubernetes.io/version\":\"v1\",\"pod-template-hash\":\"78d5dff9bf\",\"version\":\"v1\"}},\"spec\":{\"affinity\":{},\"containers\":[{\"image\":\"harbor6.wns8.io/srqz/lottery-admin-http-ui:1.0.9\",\"imagePullPolicy\":\"IfNotPresent\",\"livenessProbe\":{\"failureThreshold\":3,\"httpGet\":{\"path\":\"/\",\"port\":8080,\"scheme\":\"HTTP\"},\"initialDelaySeconds\":10,\"periodSeconds\":5,\"successThreshold\":1,\"timeoutSeconds\":1},\"name\":\"container-1v6qu9\",\"ports\":[{\"containerPort\":8080,\"name\":\"http-8080\",\"protocol\":\"TCP\"}],\"resources\":{},\"terminationMessagePath\":\"/dev/termination-log\",\"terminationMessagePolicy\":\"File\"}],\"dnsPolicy\":\"ClusterFirst\",\"restartPolicy\":\"Always\",\"schedulerName\":\"default-scheduler\",\"securityContext\":{},\"serviceAccount\":\"default\",\"serviceAccountName\":\"default\",\"terminationGracePeriodSeconds\":30}}},\"status\":{\"availableReplicas\":1,\"conditions\":[{\"lastTransitionTime\":\"2022-04-07T02:06:53Z\",\"lastUpdateTime\":\"2022-04-07T02:06:53Z\",\"message\":\"Deployment has minimum availability.\",\"reason\":\"MinimumReplicasAvailable\",\"status\":\"True\",\"type\":\"Available\"},{\"lastTransitionTime\":\"2021-12-29T01:03:13Z\",\"lastUpdateTime\":\"2022-06-03T10:37:50Z\",\"message\":\"ReplicaSet \\\"lottery-admin-http-ui-v1-769cc75d5c\\\" has successfully progressed.\",\"reason\":\"NewReplicaSetAvailable\",\"status\":\"True\",\"type\":\"Progressing\"}],\"observedGeneration\":7,\"readyReplicas\":1,\"replicas\":1,\"updatedReplicas\":1}}\n","servicemesh.kubesphere.io/enabled":"true"},"generation":10,"labels":{"app":"lottery-admin-http-ui","app.kubernetes.io/name":"srqz-admin","app.kubernetes.io/version":"v1","version":"v1"},"name":"lottery-admin-http-ui-v1","namespace":"srqz-bl003-admin"},"spec":{"progressDeadlineSeconds":600,"replicas":0,"revisionHistoryLimit":10,"selector":{"matchLabels":{"app":"lottery-admin-http-ui","app.kubernetes.io/name":"srqz-admin","app.kubernetes.io/version":"v1","version":"v1"}},"strategy":{"rollingUpdate":{"maxSurge":"25%","maxUnavailable":"25%"},"type":"RollingUpdate"},"template":{"metadata":{"annotations":{"kubesphere.io/restartedAt":"2022-06-03T10:37:46.484Z","sidecar.istio.io/inject":"true"},"creationTimestamp":null,"labels":{"app":"lottery-admin-http-ui","app.kubernetes.io/name":"srqz-admin","app.kubernetes.io/version":"v1","pod-template-hash":"78d5dff9bf","version":"v1"}},"spec":{"affinity":{},"containers":[{"image":"harbor62.wns8.io/srqz/lottery-admin-http-ui:1.0.9","imagePullPolicy":"IfNotPresent","livenessProbe":{"failureThreshold":3,"httpGet":{"path":"/","port":8080,"scheme":"HTTP"},"initialDelaySeconds":10,"periodSeconds":5,"successThreshold":1,"timeoutSeconds":1},"name":"container-1v6qu9","ports":[{"containerPort":8080,"name":"http-8080","protocol":"TCP"}],"resources":{},"terminationMessagePath":"/dev/termination-log","terminationMessagePolicy":"File"}],"dnsPolicy":"ClusterFirst","restartPolicy":"Always","schedulerName":"default-scheduler","securityContext":{},"serviceAccount":"default","serviceAccountName":"default","terminationGracePeriodSeconds":30}}}}
{"apiVersion":"apps/v1","kind":"Deployment","metadata":{"annotations":{"deployment.kubernetes.io/revision":"8","kubectl.kubernetes.io/last-applied-configuration":"{\"apiVersion\":\"apps/v1\",\"kind\":\"Deployment\",\"metadata\":{\"annotations\":{\"deployment.kubernetes.io/revision\":\"8\",\"kubesphere.io/creator\":\"admin\",\"servicemesh.kubesphere.io/enabled\":\"true\"},\"creationTimestamp\":\"2021-12-29T01:39:44Z\",\"generation\":9,\"labels\":{\"app\":\"lottery-admin-http\",\"app.kubernetes.io/name\":\"srqz-admin\",\"app.kubernetes.io/version\":\"v1\",\"version\":\"v1\"},\"name\":\"lottery-admin-http-v1\",\"namespace\":\"srqz-bl003-admin\",\"resourceVersion\":\"141293143\",\"uid\":\"9839d763-9fbb-43ed-8655-b47e47d186a3\"},\"spec\":{\"progressDeadlineSeconds\":600,\"replicas\":1,\"revisionHistoryLimit\":10,\"selector\":{\"matchLabels\":{\"app\":\"lottery-admin-http\",\"app.kubernetes.io/name\":\"srqz-admin\",\"app.kubernetes.io/version\":\"v1\",\"version\":\"v1\"}},\"strategy\":{\"rollingUpdate\":{\"maxSurge\":\"25%\",\"maxUnavailable\":\"25%\"},\"type\":\"RollingUpdate\"},\"template\":{\"metadata\":{\"annotations\":{\"kubesphere.io/restartedAt\":\"2022-06-03T10:37:50.028Z\",\"sidecar.istio.io/inject\":\"true\"},\"creationTimestamp\":null,\"labels\":{\"app\":\"lottery-admin-http\",\"app.kubernetes.io/name\":\"srqz-admin\",\"app.kubernetes.io/version\":\"v1\",\"version\":\"v1\"}},\"spec\":{\"affinity\":{},\"containers\":[{\"envFrom\":[{\"configMapRef\":{\"name\":\"app-server-config\"}},{\"configMapRef\":{\"name\":\"lottery-admin-http-config\"}}],\"image\":\"harbor6.wns8.io/srqz/lottery-admin-http:1.0.13\",\"imagePullPolicy\":\"IfNotPresent\",\"name\":\"container-glqf98\",\"ports\":[{\"containerPort\":8080,\"name\":\"http-8080\",\"protocol\":\"TCP\"}],\"resources\":{},\"terminationMessagePath\":\"/dev/termination-log\",\"terminationMessagePolicy\":\"File\",\"volumeMounts\":[{\"mountPath\":\"/etc/keystore/rabbitmq.p12\",\"name\":\"lottery-admin-http-rabbitmq-ssl\",\"subPath\":\"rabbitmq.p12\"},{\"mountPath\":\"/etc/keystore/rabbitstore.jks\",\"name\":\"lottery-admin-http-rabbitmq-ssl\",\"subPath\":\"rabbitmq.jks\"}]}],\"dnsPolicy\":\"ClusterFirst\",\"restartPolicy\":\"Always\",\"schedulerName\":\"default-scheduler\",\"securityContext\":{},\"serviceAccount\":\"default\",\"serviceAccountName\":\"default\",\"terminationGracePeriodSeconds\":30,\"volumes\":[{\"configMap\":{\"defaultMode\":292,\"name\":\"rabbitmq-ssl\"},\"name\":\"lottery-admin-http-rabbitmq-ssl\"}]}}},\"status\":{\"availableReplicas\":1,\"conditions\":[{\"lastTransitionTime\":\"2022-04-13T21:21:07Z\",\"lastUpdateTime\":\"2022-04-13T21:21:07Z\",\"message\":\"Deployment has minimum availability.\",\"reason\":\"MinimumReplicasAvailable\",\"status\":\"True\",\"type\":\"Available\"},{\"lastTransitionTime\":\"2021-12-29T01:39:44Z\",\"lastUpdateTime\":\"2022-06-03T10:37:55Z\",\"message\":\"ReplicaSet \\\"lottery-admin-http-v1-6c54544959\\\" has successfully progressed.\",\"reason\":\"NewReplicaSetAvailable\",\"status\":\"True\",\"type\":\"Progressing\"}],\"observedGeneration\":9,\"readyReplicas\":1,\"replicas\":1,\"updatedReplicas\":1}}\n","servicemesh.kubesphere.io/enabled":"true"},"generation":11,"labels":{"app":"lottery-admin-http","app.kubernetes.io/name":"srqz-admin","app.kubernetes.io/version":"v1","version":"v1"},"name":"lottery-admin-http-v1","namespace":"srqz-bl003-admin"},"spec":{"progressDeadlineSeconds":600,"replicas":0,"revisionHistoryLimit":10,"selector":{"matchLabels":{"app":"lottery-admin-http","app.kubernetes.io/name":"srqz-admin","app.kubernetes.io/version":"v1","version":"v1"}},"strategy":{"rollingUpdate":{"maxSurge":"25%","maxUnavailable":"25%"},"type":"RollingUpdate"},"template":{"metadata":{"annotations":{"kubesphere.io/restartedAt":"2022-06-03T10:37:50.028Z","sidecar.istio.io/inject":"true"},"creationTimestamp":null,"labels":{"app":"lottery-admin-http","app.kubernetes.io/name":"srqz-admin","app.kubernetes.io/version":"v1","version":"v1"}},"spec":{"affinity":{},"containers":[{"envFrom":[{"configMapRef":{"name":"app-server-config"}},{"configMapRef":{"name":"lottery-admin-http-config"}}],"image":"harbor6.wns8.io/srqz/lottery-admin-http:1.0.13","imagePullPolicy":"IfNotPresent","name":"container-glqf98","ports":[{"containerPort":8080,"name":"http-8080","protocol":"TCP"}],"resources":{},"terminationMessagePath":"/dev/termination-log","terminationMessagePolicy":"File","volumeMounts":[{"mountPath":"/etc/keystore/rabbitmq.p12","name":"lottery-admin-http-rabbitmq-ssl","subPath":"rabbitmq.p12"},{"mountPath":"/etc/keystore/rabbitstore.jks","name":"lottery-admin-http-rabbitmq-ssl","subPath":"rabbitmq.jks"}]}],"dnsPolicy":"ClusterFirst","restartPolicy":"Always","schedulerName":"default-scheduler","securityContext":{},"serviceAccount":"default","serviceAccountName":"default","terminationGracePeriodSeconds":30,"volumes":[{"configMap":{"defaultMode":292,"name":"rabbitmq-ssl"},"name":"lottery-admin-http-rabbitmq-ssl"}]}}}}
{"apiVersion":"apps/v1","kind":"Deployment","metadata":{"annotations":{"deployment.kubernetes.io/revision":"10","kubectl.kubernetes.io/last-applied-configuration":"{\"apiVersion\":\"apps/v1\",\"kind\":\"Deployment\",\"metadata\":{\"annotations\":{\"deployment.kubernetes.io/revision\":\"9\",\"kubesphere.io/creator\":\"admin\",\"servicemesh.kubesphere.io/enabled\":\"true\"},\"creationTimestamp\":\"2021-12-29T01:09:00Z\",\"generation\":10,\"labels\":{\"app\":\"lottery-shaker-manage-http-ui\",\"app.kubernetes.io/name\":\"srqz-admin\",\"app.kubernetes.io/version\":\"v1\",\"version\":\"v1\"},\"name\":\"lottery-shaker-manage-http-ui-v1\",\"namespace\":\"srqz-bl003-admin\",\"resourceVersion\":\"141293145\",\"uid\":\"e2464e72-ad1c-4787-bddd-eb1e4e4b3c74\"},\"spec\":{\"progressDeadlineSeconds\":600,\"replicas\":1,\"revisionHistoryLimit\":10,\"selector\":{\"matchLabels\":{\"app\":\"lottery-shaker-manage-http-ui\",\"app.kubernetes.io/name\":\"srqz-admin\",\"app.kubernetes.io/version\":\"v1\",\"version\":\"v1\"}},\"strategy\":{\"rollingUpdate\":{\"maxSurge\":\"25%\",\"maxUnavailable\":\"25%\"},\"type\":\"RollingUpdate\"},\"template\":{\"metadata\":{\"annotations\":{\"kubesphere.io/restartedAt\":\"2022-06-03T10:37:43.618Z\",\"sidecar.istio.io/inject\":\"true\"},\"creationTimestamp\":null,\"labels\":{\"app\":\"lottery-shaker-manage-http-ui\",\"app.kubernetes.io/name\":\"srqz-admin\",\"app.kubernetes.io/version\":\"v1\",\"version\":\"v1\"}},\"spec\":{\"affinity\":{},\"containers\":[{\"image\":\"harbor6.wns8.io/srqz/lottery-shaker-manage-http-ui:1.1.6\",\"imagePullPolicy\":\"IfNotPresent\",\"livenessProbe\":{\"failureThreshold\":3,\"httpGet\":{\"path\":\"/\",\"port\":8080,\"scheme\":\"HTTP\"},\"initialDelaySeconds\":10,\"periodSeconds\":5,\"successThreshold\":1,\"timeoutSeconds\":1},\"name\":\"container-qgvwrt\",\"ports\":[{\"containerPort\":8080,\"name\":\"http-8080\",\"protocol\":\"TCP\"}],\"resources\":{},\"terminationMessagePath\":\"/dev/termination-log\",\"terminationMessagePolicy\":\"File\"}],\"dnsPolicy\":\"ClusterFirst\",\"restartPolicy\":\"Always\",\"schedulerName\":\"default-scheduler\",\"securityContext\":{},\"serviceAccount\":\"default\",\"serviceAccountName\":\"default\",\"terminationGracePeriodSeconds\":30}}},\"status\":{\"availableReplicas\":1,\"conditions\":[{\"lastTransitionTime\":\"2022-02-08T23:38:49Z\",\"lastUpdateTime\":\"2022-02-08T23:38:49Z\",\"message\":\"Deployment has minimum availability.\",\"reason\":\"MinimumReplicasAvailable\",\"status\":\"True\",\"type\":\"Available\"},{\"lastTransitionTime\":\"2021-12-29T01:09:00Z\",\"lastUpdateTime\":\"2022-06-03T11:03:24Z\",\"message\":\"ReplicaSet \\\"lottery-shaker-manage-http-ui-v1-6688d9978\\\" has successfully progressed.\",\"reason\":\"NewReplicaSetAvailable\",\"status\":\"True\",\"type\":\"Progressing\"}],\"observedGeneration\":10,\"readyReplicas\":1,\"replicas\":1,\"updatedReplicas\":1}}\n","servicemesh.kubesphere.io/enabled":"true"},"generation":13,"labels":{"app":"lottery-shaker-manage-http-ui","app.kubernetes.io/name":"srqz-admin","app.kubernetes.io/version":"v1","version":"v1"},"name":"lottery-shaker-manage-http-ui-v1","namespace":"srqz-bl003-admin"},"spec":{"progressDeadlineSeconds":600,"replicas":0,"revisionHistoryLimit":10,"selector":{"matchLabels":{"app":"lottery-shaker-manage-http-ui","app.kubernetes.io/name":"srqz-admin","app.kubernetes.io/version":"v1","version":"v1"}},"strategy":{"rollingUpdate":{"maxSurge":"25%","maxUnavailable":"25%"},"type":"RollingUpdate"},"template":{"metadata":{"annotations":{"kubesphere.io/restartedAt":"2022-07-23T10:54:01.047Z","sidecar.istio.io/inject":"true"},"creationTimestamp":null,"labels":{"app":"lottery-shaker-manage-http-ui","app.kubernetes.io/name":"srqz-admin","app.kubernetes.io/version":"v1","version":"v1"}},"spec":{"affinity":{},"containers":[{"image":"harbor6.wns8.io/srqz/lottery-shaker-manage-http-ui:1.1.6","imagePullPolicy":"IfNotPresent","livenessProbe":{"failureThreshold":3,"httpGet":{"path":"/","port":8080,"scheme":"HTTP"},"initialDelaySeconds":10,"periodSeconds":5,"successThreshold":1,"timeoutSeconds":1},"name":"container-qgvwrt","ports":[{"containerPort":8080,"name":"http-8080","protocol":"TCP"}],"resources":{},"terminationMessagePath":"/dev/termination-log","terminationMessagePolicy":"File"}],"dnsPolicy":"ClusterFirst","restartPolicy":"Always","schedulerName":"default-scheduler","securityContext":{},"serviceAccount":"default","serviceAccountName":"default","terminationGracePeriodSeconds":30}}}}
{"apiVersion":"apps/v1","kind":"Deployment","metadata":{"annotations":{"deployment.kubernetes.io/revision":"7","kubectl.kubernetes.io/last-applied-configuration":"{\"apiVersion\":\"apps/v1\",\"kind\":\"Deployment\",\"metadata\":{\"annotations\":{\"deployment.kubernetes.io/revision\":\"6\",\"kubesphere.io/creator\":\"zhu\"},\"creationTimestamp\":\"2022-04-15T22:05:56Z\",\"generation\":7,\"labels\":{\"app\":\"promotion-event-runner-service\",\"version\":\"v1\"},\"name\":\"promotion-event-runner-service-v1\",\"namespace\":\"srqz-bl003-admin\",\"resourceVersion\":\"141293147\",\"uid\":\"bd9a7fd7-efb4-428a-b9bf-4f39d5846103\"},\"spec\":{\"progressDeadlineSeconds\":600,\"replicas\":1,\"revisionHistoryLimit\":10,\"selector\":{\"matchLabels\":{\"app\":\"promotion-event-runner-service\",\"version\":\"v1\"}},\"strategy\":{\"rollingUpdate\":{\"maxSurge\":\"25%\",\"maxUnavailable\":\"25%\"},\"type\":\"RollingUpdate\"},\"template\":{\"metadata\":{\"creationTimestamp\":null,\"labels\":{\"app\":\"promotion-event-runner-service\",\"version\":\"v1\"}},\"spec\":{\"containers\":[{\"envFrom\":[{\"configMapRef\":{\"name\":\"app-server-config\"}}],\"image\":\"harbor6.wns8.io/srqz/promotion-event-runner-service:1.0.4\",\"imagePullPolicy\":\"IfNotPresent\",\"name\":\"container-vrdm7a\",\"ports\":[{\"containerPort\":8081,\"name\":\"tcp-8081\",\"protocol\":\"TCP\"}],\"resources\":{},\"terminationMessagePath\":\"/dev/termination-log\",\"terminationMessagePolicy\":\"File\"}],\"dnsPolicy\":\"ClusterFirst\",\"restartPolicy\":\"Always\",\"schedulerName\":\"default-scheduler\",\"securityContext\":{},\"serviceAccount\":\"default\",\"serviceAccountName\":\"default\",\"terminationGracePeriodSeconds\":30}}},\"status\":{\"availableReplicas\":1,\"conditions\":[{\"lastTransitionTime\":\"2022-04-15T22:06:31Z\",\"lastUpdateTime\":\"2022-04-15T22:06:31Z\",\"message\":\"Deployment has minimum availability.\",\"reason\":\"MinimumReplicasAvailable\",\"status\":\"True\",\"type\":\"Available\"},{\"lastTransitionTime\":\"2022-04-17T22:07:08Z\",\"lastUpdateTime\":\"2022-06-03T08:08:16Z\",\"message\":\"ReplicaSet \\\"promotion-event-runner-service-v1-79dc46bb85\\\" has successfully progressed.\",\"reason\":\"NewReplicaSetAvailable\",\"status\":\"True\",\"type\":\"Progressing\"}],\"observedGeneration\":7,\"readyReplicas\":1,\"replicas\":1,\"updatedReplicas\":1}}\n"},"generation":10,"labels":{"app":"promotion-event-runner-service","version":"v1"},"name":"promotion-event-runner-service-v1","namespace":"srqz-bl003-admin"},"spec":{"progressDeadlineSeconds":600,"replicas":0,"revisionHistoryLimit":10,"selector":{"matchLabels":{"app":"promotion-event-runner-service","version":"v1"}},"strategy":{"rollingUpdate":{"maxSurge":"25%","maxUnavailable":"25%"},"type":"RollingUpdate"},"template":{"metadata":{"creationTimestamp":null,"labels":{"app":"promotion-event-runner-service","version":"v1"}},"spec":{"containers":[{"envFrom":[{"configMapRef":{"name":"app-server-config"}}],"image":"harbor62.wns8.io/srqz/promotion-event-runner-service:1.0.4","imagePullPolicy":"IfNotPresent","name":"container-vrdm7a","ports":[{"containerPort":8081,"name":"tcp-8081","protocol":"TCP"}],"resources":{},"terminationMessagePath":"/dev/termination-log","terminationMessagePolicy":"File"}],"dnsPolicy":"ClusterFirst","restartPolicy":"Always","schedulerName":"default-scheduler","securityContext":{},"serviceAccount":"default","serviceAccountName":"default","terminationGracePeriodSeconds":30}}}}
{"apiVersion":"apps/v1","kind":"Deployment","metadata":{"annotations":{"deployment.kubernetes.io/revision":"9","kubectl.kubernetes.io/last-applied-configuration":"{\"apiVersion\":\"apps/v1\",\"kind\":\"Deployment\",\"metadata\":{\"annotations\":{\"deployment.kubernetes.io/revision\":\"8\",\"kubesphere.io/creator\":\"zhu\"},\"creationTimestamp\":\"2022-04-15T22:30:43Z\",\"generation\":9,\"labels\":{\"app\":\"reconciliation-list\",\"version\":\"v1\"},\"name\":\"reconciliation-list-v1\",\"namespace\":\"srqz-bl003-admin\",\"resourceVersion\":\"141293149\",\"uid\":\"eedbc07e-fa97-4bd5-a90f-d05238fbcc2e\"},\"spec\":{\"progressDeadlineSeconds\":600,\"replicas\":1,\"revisionHistoryLimit\":10,\"selector\":{\"matchLabels\":{\"app\":\"reconciliation-list\",\"version\":\"v1\"}},\"strategy\":{\"rollingUpdate\":{\"maxSurge\":\"25%\",\"maxUnavailable\":\"25%\"},\"type\":\"RollingUpdate\"},\"template\":{\"metadata\":{\"annotations\":{\"kubesphere.io/restartedAt\":\"2022-04-15T22:31:33.802Z\"},\"creationTimestamp\":null,\"labels\":{\"app\":\"reconciliation-list\",\"version\":\"v1\"}},\"spec\":{\"containers\":[{\"envFrom\":[{\"configMapRef\":{\"name\":\"app-server-config\"}}],\"image\":\"harbor6.wns8.io/srqz/reconciliation_list:1.0.20\",\"imagePullPolicy\":\"IfNotPresent\",\"name\":\"container-h1lsad\",\"ports\":[{\"containerPort\":8081,\"name\":\"tcp-8081\",\"protocol\":\"TCP\"}],\"resources\":{},\"terminationMessagePath\":\"/dev/termination-log\",\"terminationMessagePolicy\":\"File\"}],\"dnsPolicy\":\"ClusterFirst\",\"restartPolicy\":\"Always\",\"schedulerName\":\"default-scheduler\",\"securityContext\":{},\"serviceAccount\":\"default\",\"serviceAccountName\":\"default\",\"terminationGracePeriodSeconds\":30}}},\"status\":{\"availableReplicas\":1,\"conditions\":[{\"lastTransitionTime\":\"2022-04-15T22:30:45Z\",\"lastUpdateTime\":\"2022-04-15T22:30:45Z\",\"message\":\"Deployment has minimum availability.\",\"reason\":\"MinimumReplicasAvailable\",\"status\":\"True\",\"type\":\"Available\"},{\"lastTransitionTime\":\"2022-04-15T22:30:43Z\",\"lastUpdateTime\":\"2022-06-02T07:04:28Z\",\"message\":\"ReplicaSet \\\"reconciliation-list-v1-689569b7c6\\\" has successfully progressed.\",\"reason\":\"NewReplicaSetAvailable\",\"status\":\"True\",\"type\":\"Progressing\"}],\"observedGeneration\":9,\"readyReplicas\":1,\"replicas\":1,\"updatedReplicas\":1}}\n"},"generation":12,"labels":{"app":"reconciliation-list","version":"v1"},"name":"reconciliation-list-v1","namespace":"srqz-bl003-admin"},"spec":{"progressDeadlineSeconds":600,"replicas":0,"revisionHistoryLimit":10,"selector":{"matchLabels":{"app":"reconciliation-list","version":"v1"}},"strategy":{"rollingUpdate":{"maxSurge":"25%","maxUnavailable":"25%"},"type":"RollingUpdate"},"template":{"metadata":{"annotations":{"kubesphere.io/restartedAt":"2022-04-15T22:31:33.802Z"},"creationTimestamp":null,"labels":{"app":"reconciliation-list","version":"v1"}},"spec":{"containers":[{"envFrom":[{"configMapRef":{"name":"app-server-config"}}],"image":"harbor62.wns8.io/srqz/reconciliation_list:1.0.20","imagePullPolicy":"IfNotPresent","name":"container-h1lsad","ports":[{"containerPort":8081,"name":"tcp-8081","protocol":"TCP"}],"resources":{},"terminationMessagePath":"/dev/termination-log","terminationMessagePolicy":"File"}],"dnsPolicy":"ClusterFirst","restartPolicy":"Always","schedulerName":"default-scheduler","securityContext":{},"serviceAccount":"default","serviceAccountName":"default","terminationGracePeriodSeconds":30}}}}
{"apiVersion":"apps/v1","kind":"Deployment","metadata":{"annotations":{"deployment.kubernetes.io/revision":"23","kubectl.kubernetes.io/last-applied-configuration":"{\"apiVersion\":\"apps/v1\",\"kind\":\"Deployment\",\"metadata\":{\"annotations\":{\"deployment.kubernetes.io/revision\":\"20\",\"kubesphere.io/creator\":\"zhu\"},\"creationTimestamp\":\"2022-04-15T22:26:39Z\",\"generation\":21,\"labels\":{\"app\":\"report-generation-service\",\"version\":\"v1\"},\"name\":\"report-generation-service-v1\",\"namespace\":\"srqz-bl003-admin\",\"resourceVersion\":\"141293151\",\"uid\":\"feee35e3-c363-47f2-828c-56edd8b72db9\"},\"spec\":{\"progressDeadlineSeconds\":600,\"replicas\":1,\"revisionHistoryLimit\":10,\"selector\":{\"matchLabels\":{\"app\":\"report-generation-service\",\"version\":\"v1\"}},\"strategy\":{\"rollingUpdate\":{\"maxSurge\":\"25%\",\"maxUnavailable\":\"25%\"},\"type\":\"RollingUpdate\"},\"template\":{\"metadata\":{\"annotations\":{\"kubesphere.io/restartedAt\":\"2022-04-24T17:50:31.930Z\"},\"creationTimestamp\":null,\"labels\":{\"app\":\"report-generation-service\",\"version\":\"v1\"}},\"spec\":{\"containers\":[{\"envFrom\":[{\"configMapRef\":{\"name\":\"app-server-config\"}}],\"image\":\"harbor6.wns8.io/srqz/report_generation_service:1.0.23\",\"imagePullPolicy\":\"IfNotPresent\",\"name\":\"container-z2k07n\",\"ports\":[{\"containerPort\":8081,\"name\":\"tcp-8081\",\"protocol\":\"TCP\"}],\"resources\":{},\"terminationMessagePath\":\"/dev/termination-log\",\"terminationMessagePolicy\":\"File\"}],\"dnsPolicy\":\"ClusterFirst\",\"restartPolicy\":\"Always\",\"schedulerName\":\"default-scheduler\",\"securityContext\":{},\"serviceAccount\":\"default\",\"serviceAccountName\":\"default\",\"terminationGracePeriodSeconds\":30}}},\"status\":{\"availableReplicas\":1,\"conditions\":[{\"lastTransitionTime\":\"2022-04-15T22:27:01Z\",\"lastUpdateTime\":\"2022-04-15T22:27:01Z\",\"message\":\"Deployment has minimum availability.\",\"reason\":\"MinimumReplicasAvailable\",\"status\":\"True\",\"type\":\"Available\"},{\"lastTransitionTime\":\"2022-04-15T22:26:39Z\",\"lastUpdateTime\":\"2022-06-13T04:14:52Z\",\"message\":\"ReplicaSet \\\"report-generation-service-v1-5cd9f9f585\\\" has successfully progressed.\",\"reason\":\"NewReplicaSetAvailable\",\"status\":\"True\",\"type\":\"Progressing\"}],\"observedGeneration\":21,\"readyReplicas\":1,\"replicas\":1,\"updatedReplicas\":1}}\n"},"generation":30,"labels":{"app":"report-generation-service","version":"v1"},"name":"report-generation-service-v1","namespace":"srqz-bl003-admin"},"spec":{"progressDeadlineSeconds":600,"replicas":0,"revisionHistoryLimit":10,"selector":{"matchLabels":{"app":"report-generation-service","version":"v1"}},"strategy":{"rollingUpdate":{"maxSurge":"25%","maxUnavailable":"25%"},"type":"RollingUpdate"},"template":{"metadata":{"annotations":{"kubesphere.io/restartedAt":"2022-04-24T17:50:31.930Z"},"creationTimestamp":null,"labels":{"app":"report-generation-service","version":"v1"}},"spec":{"containers":[{"envFrom":[{"configMapRef":{"name":"app-server-config"}}],"image":"harbor6.wns8.io/srqz/report_generation_service:1.0.31","imagePullPolicy":"IfNotPresent","name":"container-z2k07n","ports":[{"containerPort":8081,"name":"tcp-8081","protocol":"TCP"}],"resources":{},"terminationMessagePath":"/dev/termination-log","terminationMessagePolicy":"File"}],"dnsPolicy":"ClusterFirst","restartPolicy":"Always","schedulerName":"default-scheduler","securityContext":{},"serviceAccount":"default","serviceAccountName":"default","terminationGracePeriodSeconds":30}}}}
{"apiVersion":"apps/v1","kind":"Deployment","metadata":{"annotations":{"deployment.kubernetes.io/revision":"21","kubectl.kubernetes.io/last-applied-configuration":"{\"apiVersion\":\"apps/v1\",\"kind\":\"Deployment\",\"metadata\":{\"annotations\":{\"deployment.kubernetes.io/revision\":\"18\",\"kubesphere.io/creator\":\"admin\",\"servicemesh.kubesphere.io/enabled\":\"true\"},\"creationTimestamp\":\"2021-12-29T01:24:14Z\",\"generation\":19,\"labels\":{\"app\":\"shaker-manage-http\",\"app.kubernetes.io/name\":\"srqz-admin\",\"app.kubernetes.io/version\":\"v1\",\"version\":\"v1\"},\"name\":\"shaker-manage-http-v1\",\"namespace\":\"srqz-bl003-admin\",\"resourceVersion\":\"141293153\",\"uid\":\"102c41e9-12c6-453b-8177-6403de7266fa\"},\"spec\":{\"progressDeadlineSeconds\":600,\"replicas\":1,\"revisionHistoryLimit\":10,\"selector\":{\"matchLabels\":{\"app\":\"shaker-manage-http\",\"app.kubernetes.io/name\":\"srqz-admin\",\"app.kubernetes.io/version\":\"v1\",\"version\":\"v1\"}},\"strategy\":{\"rollingUpdate\":{\"maxSurge\":\"25%\",\"maxUnavailable\":\"25%\"},\"type\":\"RollingUpdate\"},\"template\":{\"metadata\":{\"annotations\":{\"kubesphere.io/restartedAt\":\"2022-06-03T10:37:36.804Z\",\"sidecar.istio.io/inject\":\"true\"},\"creationTimestamp\":null,\"labels\":{\"app\":\"shaker-manage-http\",\"app.kubernetes.io/name\":\"srqz-admin\",\"app.kubernetes.io/version\":\"v1\",\"version\":\"v1\"}},\"spec\":{\"affinity\":{},\"containers\":[{\"envFrom\":[{\"configMapRef\":{\"name\":\"shaker-manage-http-config\"}},{\"configMapRef\":{\"name\":\"app-server-config\"}}],\"image\":\"harbor6.wns8.io/srqz/shaker-manage-http:1.0.66\",\"imagePullPolicy\":\"IfNotPresent\",\"livenessProbe\":{\"failureThreshold\":3,\"httpGet\":{\"path\":\"/actuator/prometheus\",\"port\":10001,\"scheme\":\"HTTP\"},\"initialDelaySeconds\":10,\"periodSeconds\":5,\"successThreshold\":1,\"timeoutSeconds\":1},\"name\":\"container-me4ios\",\"ports\":[{\"containerPort\":8080,\"name\":\"http-8080\",\"protocol\":\"TCP\"},{\"containerPort\":10001,\"name\":\"https-10001\",\"protocol\":\"TCP\"}],\"resources\":{},\"terminationMessagePath\":\"/dev/termination-log\",\"terminationMessagePolicy\":\"File\",\"volumeMounts\":[{\"mountPath\":\"/etc/keystore/rabbitmq.p12\",\"name\":\"shaker-manage-http-rabbitmq-ssl\",\"subPath\":\"rabbitmq.p12\"},{\"mountPath\":\"/etc/keystore/rabbitstore.jks\",\"name\":\"shaker-manage-http-rabbitmq-ssl\",\"subPath\":\"rabbitstore.jks\"}]}],\"dnsPolicy\":\"ClusterFirst\",\"restartPolicy\":\"Always\",\"schedulerName\":\"default-scheduler\",\"securityContext\":{},\"serviceAccount\":\"default\",\"serviceAccountName\":\"default\",\"terminationGracePeriodSeconds\":30,\"volumes\":[{\"configMap\":{\"defaultMode\":292,\"name\":\"rabbitmq-ssl\"},\"name\":\"shaker-manage-http-rabbitmq-ssl\"}]}}},\"status\":{\"availableReplicas\":1,\"conditions\":[{\"lastTransitionTime\":\"2022-04-07T02:07:01Z\",\"lastUpdateTime\":\"2022-04-07T02:07:01Z\",\"message\":\"Deployment has minimum availability.\",\"reason\":\"MinimumReplicasAvailable\",\"status\":\"True\",\"type\":\"Available\"},{\"lastTransitionTime\":\"2021-12-29T01:24:14Z\",\"lastUpdateTime\":\"2022-06-03T11:02:58Z\",\"message\":\"ReplicaSet \\\"shaker-manage-http-v1-59f5649c6\\\" has successfully progressed.\",\"reason\":\"NewReplicaSetAvailable\",\"status\":\"True\",\"type\":\"Progressing\"}],\"observedGeneration\":19,\"readyReplicas\":1,\"replicas\":1,\"updatedReplicas\":1}}\n","servicemesh.kubesphere.io/enabled":"true"},"generation":24,"labels":{"app":"shaker-manage-http","app.kubernetes.io/name":"srqz-admin","app.kubernetes.io/version":"v1","version":"v1"},"name":"shaker-manage-http-v1","namespace":"srqz-bl003-admin"},"spec":{"progressDeadlineSeconds":600,"replicas":0,"revisionHistoryLimit":10,"selector":{"matchLabels":{"app":"shaker-manage-http","app.kubernetes.io/name":"srqz-admin","app.kubernetes.io/version":"v1","version":"v1"}},"strategy":{"rollingUpdate":{"maxSurge":"25%","maxUnavailable":"25%"},"type":"RollingUpdate"},"template":{"metadata":{"annotations":{"kubesphere.io/restartedAt":"2022-06-03T10:37:36.804Z","sidecar.istio.io/inject":"true"},"creationTimestamp":null,"labels":{"app":"shaker-manage-http","app.kubernetes.io/name":"srqz-admin","app.kubernetes.io/version":"v1","version":"v1"}},"spec":{"affinity":{},"containers":[{"envFrom":[{"configMapRef":{"name":"shaker-manage-http-config"}},{"configMapRef":{"name":"app-server-config"}}],"image":"harbor6.wns8.io/srqz/shaker-manage-http:1.1.1","imagePullPolicy":"IfNotPresent","livenessProbe":{"failureThreshold":3,"httpGet":{"path":"/actuator/prometheus","port":10001,"scheme":"HTTP"},"initialDelaySeconds":10,"periodSeconds":5,"successThreshold":1,"timeoutSeconds":1},"name":"container-me4ios","ports":[{"containerPort":8080,"name":"http-8080","protocol":"TCP"},{"containerPort":10001,"name":"https-10001","protocol":"TCP"}],"resources":{},"terminationMessagePath":"/dev/termination-log","terminationMessagePolicy":"File","volumeMounts":[{"mountPath":"/etc/keystore/rabbitmq.p12","name":"shaker-manage-http-rabbitmq-ssl","subPath":"rabbitmq.p12"},{"mountPath":"/etc/keystore/rabbitstore.jks","name":"shaker-manage-http-rabbitmq-ssl","subPath":"rabbitstore.jks"}]}],"dnsPolicy":"ClusterFirst","restartPolicy":"Always","schedulerName":"default-scheduler","securityContext":{},"serviceAccount":"default","serviceAccountName":"default","terminationGracePeriodSeconds":30,"volumes":[{"configMap":{"defaultMode":292,"name":"rabbitmq-ssl"},"name":"shaker-manage-http-rabbitmq-ssl"}]}}}}
