{"apiVersion":"v1","kind":"Service","metadata":{"annotations":{"kubesphere.io/serviceType":"statelessservice"},"labels":{"app":"woshop-admin","version":"v1"},"name":"woshop-admin","namespace":"wo-shop"},"spec":{"ports":[{"name":"http-shop","port":80,"protocol":"TCP","targetPort":80}],"selector":{"app":"woshop-admin"},"sessionAffinity":"None","type":"ClusterIP"}}
{"apiVersion":"v1","kind":"Service","metadata":{"annotations":{"kubesphere.io/serviceType":"statelessservice"},"labels":{"app":"woshop-custom","version":"v1"},"name":"woshop-custom","namespace":"wo-shop"},"spec":{"ports":[{"name":"http-cus","port":80,"protocol":"TCP","targetPort":80}],"selector":{"app":"woshop-custom"},"sessionAffinity":"None","type":"ClusterIP"}}
{"apiVersion":"v1","kind":"Service","metadata":{"annotations":{"kubesphere.io/serviceType":"statelessservice"},"labels":{"app":"woshop-merch","version":"v1"},"name":"woshop-merch","namespace":"wo-shop"},"spec":{"ports":[{"name":"http-merch","port":80,"protocol":"TCP","targetPort":80}],"selector":{"app":"woshop-merch"},"sessionAffinity":"None","type":"ClusterIP"}}
{"apiVersion":"v1","kind":"Service","metadata":{"annotations":{"kubesphere.io/serviceType":"statelessservice"},"labels":{"app":"woshop-ws","version":"v1"},"name":"woshop-ws","namespace":"wo-shop"},"spec":{"ports":[{"name":"http-ws","port":8273,"protocol":"TCP","targetPort":8273}],"selector":{"app":"woshop-ws"},"sessionAffinity":"None","type":"ClusterIP"}}
